amorf/__init__.py
amorf/datasets.py
amorf/metrics.py
amorf/multiOutputSVR.py
amorf/neuralNetRegression.py
amorf/probabalisticRegression.py
amorf/problemTransformation.py
amorf/utils.py
examples/cross_validations/AutoEncoderRegression_CV.py
examples/cross_validations/NN_CV.py
examples/cross_validations/SingleTarget_CV.py
examples/cross_validations/__init__.py
examples/cross_validations/probabalisticRegression_CV.py
amorf-0.0.5.dist-info/LICENSE.txt
amorf-0.0.5.dist-info/METADATA
amorf-0.0.5.dist-info/WHEEL
amorf-0.0.5.dist-info/top_level.txt
amorf-0.0.5.dist-info/RECORD
